README.md
setup.py
landroidcc/__init__.py
landroidcc/_about_.py
landroidcc/cmdclient.py
landroidcc.egg-info/PKG-INFO
landroidcc.egg-info/SOURCES.txt
landroidcc.egg-info/dependency_links.txt
landroidcc.egg-info/entry_points.txt
landroidcc.egg-info/requires.txt
landroidcc.egg-info/top_level.txt
tests/__init__.py
tests/test_mower.py