Metadata-Version: 2.1
Name: landroidcc
Version: 0.1.2
Summary: Accessing landroid mowers through the cloud
Home-page: UNKNOWN
Author: Alexander Weggerle
Author-email: alexander@weggerle.de
License: UNKNOWN
Platform: UNKNOWN
Classifier: Programming Language :: Python :: 2.7
Classifier: Programming Language :: Python :: 3
Classifier: Programming Language :: Python :: 3.6
Classifier: Programming Language :: Python :: 3.7
Classifier: Programming Language :: Python :: 3.8
Classifier: License :: OSI Approved :: MIT License
Classifier: Operating System :: OS Independent
Classifier: Development Status :: 3 - Alpha
